osgithub/__init__.py
osgithub/github.py
osgithub-0.5.0.dist-info/LICENSE
osgithub-0.5.0.dist-info/METADATA
osgithub-0.5.0.dist-info/WHEEL
osgithub-0.5.0.dist-info/top_level.txt
osgithub-0.5.0.dist-info/RECORD
